voltengine/__init__.py
voltengine/accounting/__init__.py
voltengine/accounting/ledger_engine.py
voltengine/billing/__init__.py
voltengine/billing/prepaid_daily.py
voltengine/billing/prepaid_monthly.py
voltengine/engine/__init__.py
voltengine/engine/billing_engine.py
voltengine/engine/context.py
voltengine/engine/response.py
voltengine/models/__init__.py
voltengine/models/consumer.py
voltengine/models/ledger.py
voltengine/models/meter.py
voltengine/models/period.py
voltengine/models/tariff.py
voltengine/operations/__init__.py
voltengine/operations/dps.py
voltengine/operations/excess_demand.py
voltengine/operations/installment.py
voltengine/operations/load_change.py
voltengine/operations/recharge.py
voltengine/operations/slab_tariff.py
voltengine/operations/wallet.py
voltengine/tariff/__init__.py
voltengine/tariff/slab.py
voltengine/tariff/tariff_change.py
voltengine-0.1.2.dist-info/licenses/LICENSE
voltengine-0.1.2.dist-info/METADATA
voltengine-0.1.2.dist-info/WHEEL
voltengine-0.1.2.dist-info/top_level.txt
voltengine-0.1.2.dist-info/RECORD
