Metadata-Version: 2.4
Name: voltengine
Version: 0.1.2
Summary: Utility-grade electricity billing engine supporting prepaid, LT and HT consumers
Author-email: Abhinandan <abhinandanroy165@gmail.com>
License: MIT
Keywords: electricity,billing,prepaid,smart-meter,utility,amisps
Classifier: Programming Language :: Python :: 3
Classifier: License :: OSI Approved :: MIT License
Classifier: Operating System :: OS Independent
Requires-Python: >=3.8
License-File: LICENSE
Dynamic: license-file
